tagmapper/__init__.py
tagmapper/connector_api.py
tagmapper/facility.py
tagmapper/generic_model.py
tagmapper/mapped_object.py
tagmapper/mapping.py
tagmapper/schemas.py
tagmapper/spd_classes/base_model.py
tagmapper/spd_classes/pipe.py
tagmapper/spd_classes/separator.py
tagmapper/spd_classes/well.py
tagmapper-0.8.2.dist-info/METADATA
tagmapper-0.8.2.dist-info/WHEEL
tagmapper-0.8.2.dist-info/RECORD
