Metadata-Version: 2.1
Name: tagmapper
Version: 0.8.2
Summary: Python wrapper for Equinor SPD tag mapping database
Author: Åsmund Våge Fannemel
Author-email: asmf@equinor.com
Requires-Python: >=3.10.0,<4.0
Classifier: Programming Language :: Python :: 3
Classifier: Programming Language :: Python :: 3.10
Classifier: Programming Language :: Python :: 3.11
Classifier: Programming Language :: Python :: 3.12
Requires-Dist: certifi (>=2025.1.31)
Requires-Dist: commonlib-reader (>=1.1.0,<2.0.0)
Requires-Dist: eq-api-connector (>=1.0.0,<2.0.0)
Requires-Dist: pandas (>=2.2.2,<3.0.0)
Requires-Dist: pyyaml (>=6.0.2,<7.0.0)
